typecast/__init__.py
typecast/converter.py
typecast/date.py
typecast/formats.py
typecast/guess.py
typecast/name.py
typecast/value.py
typecast-0.3.3.dist-info/DESCRIPTION.rst
typecast-0.3.3.dist-info/METADATA
typecast-0.3.3.dist-info/metadata.json
typecast-0.3.3.dist-info/namespace_packages.txt
typecast-0.3.3.dist-info/RECORD
typecast-0.3.3.dist-info/top_level.txt
typecast-0.3.3.dist-info/WHEEL
