Metadata-Version: 2.0
Name: typecast
Version: 0.3.3
Summary: Convert types in source data.
Home-page: http://github.com/pudo/typecast
Author: Friedrich Lindenberg
Author-email: friedrich@pudo.org
License: MIT
Keywords: types rdf
Platform: UNKNOWN
Classifier: Development Status :: 3 - Alpha
Classifier: Intended Audience :: Developers
Classifier: License :: OSI Approved :: MIT License
Classifier: Operating System :: OS Independent
Classifier: Programming Language :: Python :: 2.6
Classifier: Programming Language :: Python :: 2.7
Classifier: Programming Language :: Python :: 3.3
Classifier: Programming Language :: Python :: 3.4
Requires-Dist: python-dateutil (>=1.5)
Requires-Dist: normality
Requires-Dist: six
